playlistconverterlite/__init__.py
playlistconverterlite/converter.py
playlistconverterlite-0.0.2.dist-info/LICENSE.txt
playlistconverterlite-0.0.2.dist-info/METADATA
playlistconverterlite-0.0.2.dist-info/WHEEL
playlistconverterlite-0.0.2.dist-info/top_level.txt
playlistconverterlite-0.0.2.dist-info/RECORD
