Metadata-Version: 2.1
Name: playlistconverterlite
Version: 0.0.2
Summary: Apple Music to Spotify playlist converter
Home-page: https://github.com/andrewking1597/playlist-converter-lite
Author: Andrew King
Author-email: andrewking1597@gmail.com
License: UNKNOWN
Platform: UNKNOWN
License-File: LICENSE.txt
Requires-Dist: apple-music-python
Requires-Dist: spotipy
